README.md
setup.py
bin/yamas
yamas/__init__.py
yamas/config.py
yamas/ex.py
yamas/handler.py
yamas/reqresp.py
yamas/respgen.py
yamas/server.py
yamas.egg-info/PKG-INFO
yamas.egg-info/SOURCES.txt
yamas.egg-info/dependency_links.txt
yamas.egg-info/requires.txt
yamas.egg-info/top_level.txt
yamas.egg-info/zip-safe