Metadata-Version: 2.1
Name: yamas
Version: 0.2.1
Summary: Yamas - Yet Another Mock API Server
Home-page: https://github.com/yam-ai/yamas
Author: Thomas Lee
Author-email: thomaslee@yam.ai
License: UNKNOWN
Keywords: rest api mocking server
Platform: UNKNOWN
Classifier: Development Status :: 3 - Alpha
Classifier: License :: OSI Approved :: Apache Software License
Classifier: Programming Language :: Python :: 3.6
Classifier: Topic :: Software Development :: Testing :: Mocking
Requires-Python: >=3.6
